HISTORY.rst
LICENSE
MANIFEST.in
README.rst
setup.cfg
setup.py
django_inventory/__init__.py
django_inventory/urls.py
django_inventory/wsgi.py
django_inventory.egg-info/PKG-INFO
django_inventory.egg-info/SOURCES.txt
django_inventory.egg-info/dependency_links.txt
django_inventory.egg-info/not-zip-safe
django_inventory.egg-info/requires.txt
django_inventory.egg-info/top_level.txt
django_inventory/apps/assets/__init__.py
django_inventory/apps/assets/admin.py
django_inventory/apps/assets/forms.py
django_inventory/apps/assets/models.py
django_inventory/apps/assets/urls.py
django_inventory/apps/assets/views.py
django_inventory/apps/assets/conf/__init__.py
django_inventory/apps/assets/conf/settings.py
django_inventory/apps/assets/locale/en/LC_MESSAGES/django.po
django_inventory/apps/assets/locale/es/LC_MESSAGES/django.mo
django_inventory/apps/assets/locale/es/LC_MESSAGES/django.po
django_inventory/apps/assets/locale/ru/LC_MESSAGES/django.mo
django_inventory/apps/assets/locale/ru/LC_MESSAGES/django.po
django_inventory/apps/assets/templates/assets/state_subtemplate.html
django_inventory/apps/assets/templatetags/__init__.py
django_inventory/apps/assets/templatetags/assets_tags.py
django_inventory/apps/common/__init__.py
django_inventory/apps/common/api.py
django_inventory/apps/common/models.py
django_inventory/apps/common/urls.py
django_inventory/apps/common/utils.py
django_inventory/apps/common/views.py
django_inventory/apps/common/conf/__init__.py
django_inventory/apps/common/conf/settings.py
django_inventory/apps/common/locale/en/LC_MESSAGES/django.po
django_inventory/apps/common/locale/es/LC_MESSAGES/django.mo
django_inventory/apps/common/locale/es/LC_MESSAGES/django.po
django_inventory/apps/common/locale/ru/LC_MESSAGES/django.mo
django_inventory/apps/common/locale/ru/LC_MESSAGES/django.po
django_inventory/apps/common/middleware/__init__.py
django_inventory/apps/common/middleware/login_required_middleware.py
django_inventory/apps/common/migrations/0001_initial.py
django_inventory/apps/common/migrations/__init__.py
django_inventory/apps/common/templates/common/404.html
django_inventory/apps/common/templates/common/500.html
django_inventory/apps/common/templates/common/login.html
