Metadata-Version: 1.1
Name: django-inventory
Version: 1.0.rc1
Summary: Free Open Source Inventory and Fixed Assets Control System.
Home-page: https://github.com/rosarior/django-inventory
Author: Roberto Rosario
Author-email: roberto.rosario@gmail.com
License:    Copyright 2011 Roberto Rosario
